kfp/__init__.py
kfp/init_test.py
kfp/version.py
kfp/cli/__init__.py
kfp/cli/__main__.py
kfp/cli/cli.py
kfp/cli/cli_test.py
kfp/cli/compile_.py
kfp/cli/compile_test.py
kfp/cli/component.py
kfp/cli/component_test.py
kfp/cli/diagnose_me_cli.py
kfp/cli/dsl.py
kfp/cli/experiment.py
kfp/cli/output.py
kfp/cli/pipeline.py
kfp/cli/recurring_run.py
kfp/cli/run.py
kfp/cli/diagnose_me/__init__.py
kfp/cli/diagnose_me/dev_env.py
kfp/cli/diagnose_me/dev_env_test.py
kfp/cli/diagnose_me/gcp.py
kfp/cli/diagnose_me/gcp_test.py
kfp/cli/diagnose_me/kubernetes_cluster.py
kfp/cli/diagnose_me/kubernetes_cluster_test.py
kfp/cli/diagnose_me/utility.py
kfp/cli/diagnose_me/utility_test.py
kfp/cli/utils/__init__.py
kfp/cli/utils/aliased_plurals_group.py
kfp/cli/utils/aliased_plurals_group_test.py
kfp/cli/utils/deprecated_alias_group.py
kfp/cli/utils/deprecated_alias_group_test.py
kfp/cli/utils/parsing.py
kfp/cli/utils/parsing_test.py
kfp/client/__init__.py
kfp/client/auth.py
kfp/client/auth_test.py
kfp/client/client.py
kfp/client/client_test.py
kfp/client/set_volume_credentials.py
kfp/client/set_volume_credentials_test.py
kfp/client/token_credentials_base.py
kfp/client/token_credentials_base_test.py
kfp/compiler/__init__.py
kfp/compiler/compiler.py
kfp/compiler/compiler_test.py
kfp/compiler/compiler_utils.py
kfp/compiler/compiler_utils_test.py
kfp/compiler/pipeline_spec_builder.py
kfp/compiler/pipeline_spec_builder_test.py
kfp/components/__init__.py
kfp/components/load_yaml_utilities.py
kfp/components/load_yaml_utilities_test.py
kfp/dsl/__init__.py
kfp/dsl/base_component.py
kfp/dsl/base_component_test.py
kfp/dsl/component_decorator.py
kfp/dsl/component_decorator_test.py
kfp/dsl/component_factory.py
kfp/dsl/component_factory_test.py
kfp/dsl/component_task_config.py
kfp/dsl/constants.py
kfp/dsl/container_component_artifact_channel.py
kfp/dsl/container_component_artifact_channel_test.py
kfp/dsl/container_component_class.py
kfp/dsl/container_component_decorator.py
kfp-2.15.2.dist-info/METADATA
kfp-2.15.2.dist-info/WHEEL
kfp-2.15.2.dist-info/entry_points.txt
kfp-2.15.2.dist-info/top_level.txt
kfp-2.15.2.dist-info/RECORD
