Metadata-Version: 2.4
Name: kfp
Version: 2.15.2
Summary: Kubeflow Pipelines SDK
Home-page: https://github.com/kubeflow/pipelines
Author: The Kubeflow Authors
Project-URL: Documentation, https://kubeflow-pipelines.readthedocs.io/en/stable/
Project-URL: Bug Tracker, https://github.com/kubeflow/pipelines/issues
Project-URL: Source, https://github.com/kubeflow/pipelines/tree/master/sdk
Project-URL: Changelog, https://github.com/kubeflow/pipelines/blob/master/sdk/RELEASE.md
Classifier: Intended Audience :: Developers
Classifier: Intended Audience :: Education
Classifier: Intended Audience :: Science/Research
Classifier: License :: OSI Approved :: Apache Software License
Classifier: Programming Language :: Python :: 3
Classifier: Programming Language :: Python :: 3.9
Classifier: Programming Language :: Python :: 3.10
Classifier: Programming Language :: Python :: 3.11
Classifier: Programming Language :: Python :: 3.12
Classifier: Programming Language :: Python :: 3.13
Classifier: Topic :: Scientific/Engineering
Classifier: Topic :: Scientific/Engineering :: Artificial Intelligence
Classifier: Topic :: Software Development
Classifier: Topic :: Software Development :: Libraries
Classifier: Topic :: Software Development :: Libraries :: Python Modules
Requires-Python: >=3.9.0
Requires-Dist: click>=8.1.8
Requires-Dist: click-option-group==0.5.7
Requires-Dist: docstring-parser<1,>=0.7.3
Requires-Dist: google-api-core!=2.0.*,!=2.1.*,!=2.2.*,!=2.3.0,<3.0.0dev,>=1.31.5
Requires-Dist: google-auth<3,>=1.6.1
Requires-Dist: google-cloud-storage<4,>=2.2.1
Requires-Dist: kfp-pipeline-spec<3,>=2.15.0
Requires-Dist: kfp-server-api<3,>=2.15.0
Requires-Dist: kubernetes<31,>=8.0.0
Requires-Dist: protobuf<7.0,>=6.31.1
Requires-Dist: PyYAML<7,>=5.3
Requires-Dist: requests-toolbelt<2,>=0.8.0
Requires-Dist: tabulate<1,>=0.8.6
Requires-Dist: urllib3<3.0.0
Requires-Dist: typing-extensions<5,>=3.7.4; python_version < "3.9"
Provides-Extra: all
Requires-Dist: docker; extra == "all"
Requires-Dist: kfp-kubernetes==2.15.2; extra == "all"
Requires-Dist: nbclient<1,>=0.10; extra == "all"
Requires-Dist: ipykernel<7,>=6; extra == "all"
Requires-Dist: jupyter_client<9,>=7; extra == "all"
Provides-Extra: kubernetes
Requires-Dist: kfp-kubernetes==2.15.2; extra == "kubernetes"
Provides-Extra: notebooks
Requires-Dist: nbclient<1,>=0.10; extra == "notebooks"
Requires-Dist: ipykernel<7,>=6; extra == "notebooks"
Requires-Dist: jupyter_client<9,>=7; extra == "notebooks"
Dynamic: author
Dynamic: classifier
Dynamic: description
Dynamic: description-content-type
Dynamic: home-page
Dynamic: project-url
Dynamic: provides-extra
Dynamic: requires-dist
Dynamic: requires-python
Dynamic: summary
